syntaxforest/__init__.py
syntaxforest/forms.py
syntaxforest/models.py
syntaxforest/settings.py
syntaxforest/urls.py
syntaxforest/views.py
syntaxforest/wsgi.py
syntaxforest-1.0.3.dist-info/LICENSE
syntaxforest-1.0.3.dist-info/METADATA
syntaxforest-1.0.3.dist-info/WHEEL
syntaxforest-1.0.3.dist-info/top_level.txt
syntaxforest-1.0.3.dist-info/RECORD
