Metadata-Version: 2.1
Name: syntaxforest
Version: 1.0.3
Summary: Syntax Forest
Home-page: https://github.com/grantjenks/syntaxforest
Author: Grant Jenks
Author-email: contact@grantjenks.com
License: Apache 2.0
Project-URL: Documentation, https://syntaxforest.com
Project-URL: Source, https://github.com/grantjenks/syntaxforest
Project-URL: Tracker, https://github.com/grantjenks/syntaxforest/issues
Platform: UNKNOWN
Classifier: Development Status :: 5 - Production/Stable
Classifier: Intended Audience :: Developers
Classifier: License :: OSI Approved :: Apache Software License
Classifier: Natural Language :: English
Classifier: Programming Language :: Python
Classifier: Programming Language :: Python :: 3
Classifier: Programming Language :: Python :: Implementation :: CPython
License-File: LICENSE
Requires-Dist: Django (==3.2.*)
Requires-Dist: lxml
Requires-Dist: modelqueue
Requires-Dist: pygments
Requires-Dist: tree-sitter-languages
